snvmodels/__init__.py
snvmodels/chromacmapper/__init__.py
snvmodels/chromacmapper/chromacmapper.py
snvmodels/chromacmapper/creators/__init__.py
snvmodels/chromacmapper/creators/ncbichromacmappercreator.py
snvmodels/converters/__init__.py
snvmodels/converters/cpratocspraconverter.py
snvmodels/converters/cpratocspragrch37converter.py
snvmodels/converters/cpratospraconverter.py
snvmodels/converters/cpratospragrch37converter.py
snvmodels/cpra/__init__.py
snvmodels/cpra/cpra.py
snvmodels/cpra/formatters/__init__.py
snvmodels/cpra/formatters/cprahgvschrformatter.py
snvmodels/cpra/formatters/cpraoncokbgenomicchangeformatter.py
snvmodels/spra/__init__.py
snvmodels/spra/cspra.py
snvmodels/spra/spra.py
tests/__init__.py
tests/chromacmapper/__init__.py
tests/chromacmapper/test_chromacmapper_grch37.py
tests/chromacmapper/creators/__init__.py
tests/chromacmapper/creators/test_ncbichromacmappercreator_grch37p13.py
tests/converters/__init__.py
tests/converters/test_cpratocspraconverter.py
tests/converters/test_cpratocspragrch37converter.py
tests/converters/test_cpratospraconverter.py
tests/converters/test_cpratospragrch37converter.py
tests/cpra/__init__.py
tests/cpra/test_cpra.py
tests/cpra/formatters/__init__.py
tests/cpra/formatters/test_cprahgvschrformatter.py
tests/cpra/formatters/test_cpraoncokbgenomicchangeformatter.py
tests/spra/__init__.py
tests/spra/test_cspra.py
tests/spra/test_spra.py
snvmodels-0.0.3.dist-info/METADATA
snvmodels-0.0.3.dist-info/WHEEL
snvmodels-0.0.3.dist-info/top_level.txt
snvmodels-0.0.3.dist-info/RECORD
