Metadata-Version: 2.1
Name: snvmodels
Version: 0.0.3
Summary: SNV data models and converters
Home-page: https://github.com/markgene/snvmodels
Author: Mark J Chen
Author-email: mjchen.gene@gmail.com
Classifier: Programming Language :: Python :: 3
Classifier: License :: OSI Approved :: MIT License
Classifier: Operating System :: OS Independent
Requires-Python: >=3.6
Requires-Dist: appdirs
Requires-Dist: requests
